taxon/__init__.py
taxon-0.0.1.dist-info/DESCRIPTION.rst
taxon-0.0.1.dist-info/METADATA
taxon-0.0.1.dist-info/RECORD
taxon-0.0.1.dist-info/WHEEL
taxon-0.0.1.dist-info/metadata.json
taxon-0.0.1.dist-info/top_level.txt
