Metadata-Version: 2.0
Name: taxon
Version: 0.0.1
Summary: Taxon
Home-page: https://github.com/kislyuk/taxon
Author: Andrey Kislyuk
Author-email: kislyuk@gmail.com
License: Apache Software License
Project-URL: Documentation, https://kislyuk.github.io/taxon
Project-URL: Source Code, https://github.com/kislyuk/taxon
Project-URL: Issue Tracker, https://github.com/kislyuk/taxon/issues
Platform: UNKNOWN
